{
  "generatedAt": "2026-04-24T07:17:01.224914Z",
  "stocks": {
    "Caterpillar Marine": {
      "ticker": "CAT",
      "exchange": "NYSE",
      "note": "Parent company Caterpillar Inc",
      "price": 835.24,
      "currency": "USD",
      "change": 24.29,
      "changePct": 3.0,
      "updatedAt": "2026-04-24T07:17:01.224914Z"
    },
    "Kongsberg Maritime": {
      "ticker": "KOG.OL",
      "exchange": "Oslo B\u00f8rs",
      "note": "Parent company Kongsberg Gruppen ASA",
      "price": 319.5,
      "currency": "NOK",
      "change": -7.3,
      "changePct": -2.23,
      "updatedAt": "2026-04-24T07:17:01.224914Z"
    },
    "Bureau Veritas": {
      "ticker": "BVI.PA",
      "exchange": "Euronext Paris",
      "note": null,
      "price": 25.52,
      "currency": "EUR",
      "change": -0.2,
      "changePct": -0.78,
      "updatedAt": "2026-04-24T07:17:01.224914Z"
    },
    "W\u00e4rtsil\u00e4": {
      "ticker": "WRT1V.HE",
      "exchange": "Nasdaq Helsinki",
      "note": null,
      "price": 38.5,
      "currency": "EUR",
      "change": -1.13,
      "changePct": -2.85,
      "updatedAt": "2026-04-24T07:17:01.224914Z"
    },
    "Shell Nederland": {
      "ticker": "SHEL.L",
      "exchange": "London Stock Exchange",
      "note": "Parent company Shell plc",
      "price": 3324.0,
      "currency": "GBp",
      "change": 23.5,
      "changePct": 0.71,
      "updatedAt": "2026-04-24T07:17:01.224914Z"
    },
    "BP Raffinaderij Rotterdam": {
      "ticker": "BP.L",
      "exchange": "London Stock Exchange",
      "note": "Parent company BP plc",
      "price": 575.9,
      "currency": "GBp",
      "change": 5.9,
      "changePct": 1.04,
      "updatedAt": "2026-04-24T07:17:01.224914Z"
    },
    "RWE Renewables": {
      "ticker": "RWE.DE",
      "exchange": "XETRA",
      "note": "Parent company RWE AG",
      "price": 60.46,
      "currency": "EUR",
      "change": 0.0,
      "changePct": 0.0,
      "updatedAt": "2026-04-24T07:17:01.224914Z"
    },
    "\u00d8rsted": {
      "ticker": "ORSTED.CO",
      "exchange": "Nasdaq Copenhagen",
      "note": null,
      "price": 163.6,
      "currency": "DKK",
      "change": 0.1,
      "changePct": 0.06,
      "updatedAt": "2026-04-24T07:17:01.224914Z"
    },
    "SSE Renewables": {
      "ticker": "SSE.L",
      "exchange": "London Stock Exchange",
      "note": "Parent company SSE plc",
      "price": 2650.9719,
      "currency": "GBp",
      "change": -17.0281,
      "changePct": -0.64,
      "updatedAt": "2026-04-24T07:17:01.224914Z"
    },
    "TotalEnergies": {
      "ticker": "TTE.PA",
      "exchange": "Euronext Paris",
      "note": null,
      "price": 77.37,
      "currency": "EUR",
      "change": 0.54,
      "changePct": 0.7,
      "updatedAt": "2026-04-24T07:17:01.224914Z"
    },
    "DEME Group": {
      "ticker": "DEME.BR",
      "exchange": "Euronext Brussels",
      "note": null,
      "price": 183.2,
      "currency": "EUR",
      "change": -1.4,
      "changePct": -0.76,
      "updatedAt": "2026-04-24T07:17:01.224914Z"
    },
    "ArcelorMittal": {
      "ticker": "MT.AS",
      "exchange": "Euronext Amsterdam",
      "note": null,
      "price": 50.74,
      "currency": "EUR",
      "change": -1.22,
      "changePct": -2.35,
      "updatedAt": "2026-04-24T07:17:01.224914Z"
    },
    "Equinor": {
      "ticker": "EQNR.OL",
      "exchange": "Oslo B\u00f8rs",
      "note": null,
      "price": 362.3,
      "currency": "NOK",
      "change": 7.0,
      "changePct": 1.97,
      "updatedAt": "2026-04-24T07:17:01.224914Z"
    },
    "Yara International": {
      "ticker": "YAR.OL",
      "exchange": "Oslo B\u00f8rs",
      "note": null,
      "price": 559.0,
      "currency": "NOK",
      "change": 26.6,
      "changePct": 5.0,
      "updatedAt": "2026-04-24T07:17:01.224914Z"
    },
    "ExxonMobil": {
      "ticker": "XOM",
      "exchange": "NYSE",
      "note": null,
      "price": 150.53,
      "currency": "USD",
      "change": 1.11,
      "changePct": 0.74,
      "updatedAt": "2026-04-24T07:17:01.224914Z"
    },
    "Tata Steel": {
      "ticker": "TATASTEEL.NS",
      "exchange": "NSE India",
      "note": null,
      "price": 210.33,
      "currency": "INR",
      "change": -0.27,
      "changePct": -0.13,
      "updatedAt": "2026-04-24T07:17:01.224914Z"
    },
    "DFDS": {
      "ticker": "DFDS.CO",
      "exchange": "Nasdaq Copenhagen",
      "note": null,
      "price": 154.2,
      "currency": "DKK",
      "change": -0.3,
      "changePct": -0.19,
      "updatedAt": "2026-04-24T07:17:01.224914Z"
    }
  }
}
